scikit_sundae-1.1.0.dist-info/RECORD
scikit_sundae-1.1.0.dist-info/WHEEL
scikit_sundae-1.1.0.dist-info/top_level.txt
scikit_sundae-1.1.0.dist-info/METADATA
scikit_sundae-1.1.0.dist-info/licenses/LICENSES_bundled
scikit_sundae-1.1.0.dist-info/licenses/LICENSE
sksundae/c_config.pxi
sksundae/py_config.pxi
sksundae/_cy_ida.pyx
sksundae/_cy_common.pxd
sksundae/c_cvode.pxd
sksundae/c_nvector.pxd
sksundae/c_ida.pxd
sksundae/_cy_cvode.pyx
sksundae/__init__.py
sksundae/_cy_cvode.cpython-313-darwin.so
sksundae/jacband.py
sksundae/c_sundials.pxd
sksundae/utils.py
sksundae/_cy_ida.cpython-313-darwin.so
sksundae/_cy_common.pyx
sksundae/c_sunmatrix.pxd
sksundae/c_sunlinsol.pxd
sksundae/_cy_common.cpython-313-darwin.so
sksundae/cvode/_precond.py
sksundae/cvode/__init__.py
sksundae/cvode/_jactimes.py
sksundae/cvode/_solver.py
sksundae/include/lapackdense_wrapper.h
sksundae/include/superlumt_wrapper.h
sksundae/include/lapackband_wrapper.h
sksundae/.dylibs/libsundials_nvecserial.7.5.0.dylib
sksundae/.dylibs/libsundials_sunlinsolband.5.5.0.dylib
sksundae/.dylibs/libsundials_sunlinsolsptfqmr.5.5.0.dylib
sksundae/.dylibs/libsundials_cvode.7.5.0.dylib
sksundae/.dylibs/libomp.dylib
sksundae/.dylibs/libsundials_sunlinsolspbcgs.5.5.0.dylib
sksundae/.dylibs/libopenblasp-r0.3.30.dylib
sksundae/.dylibs/libsundials_sunlinsoldense.5.5.0.dylib
sksundae/.dylibs/libsundials_sunmatrixsparse.5.5.0.dylib
sksundae/.dylibs/libgfortran.5.dylib
sksundae/.dylibs/libsundials_core.7.5.0.dylib
sksundae/.dylibs/libsundials_sunmatrixdense.5.5.0.dylib
sksundae/.dylibs/libsundials_sunlinsolspgmr.5.5.0.dylib
sksundae/.dylibs/libsundials_ida.7.5.0.dylib
sksundae/.dylibs/libsundials_sunlinsollapackdense.5.5.0.dylib
sksundae/.dylibs/libsundials_sunmatrixband.5.5.0.dylib
sksundae/.dylibs/libquadmath.0.dylib
sksundae/.dylibs/libgcc_s.1.1.dylib
sksundae/.dylibs/libsundials_sunlinsollapackband.5.5.0.dylib
sksundae/.dylibs/libsundials_sunlinsolsuperlumt.5.5.0.dylib
sksundae/ida/_precond.py
sksundae/ida/__init__.py
sksundae/ida/_jactimes.py
sksundae/ida/_solver.py
