Metadata-Version: 2.4
Name: scikit-sundae
Version: 1.1.0
Summary: Python bindings to SUNDIALS differential aglebraic equation solvers.
Author: Corey R. Randall
Author-email: corey.randall@nrel.gov
Maintainer: Corey R. Randall
Maintainer-email: corey.randall@nrel.gov
License-Expression: BSD-3-Clause
Project-URL: Homepage, https://github.com/NREL/scikit-sundae
Project-URL: Documentation, https://scikit-sundae.readthedocs.io/
Project-URL: Repository, https://github.com/NREL/scikit-sundae
Project-URL: Issues, https://github.com/NREL/scikit-sundae/issues
Keywords: sundials,dae,ode,integrator,ivp,cvode,ida
Classifier: Development Status :: 5 - Production/Stable
Classifier: Intended Audience :: Science/Research
Classifier: Topic :: Scientific/Engineering :: Mathematics
Classifier: Programming Language :: Python :: 3
Classifier: Programming Language :: Python :: 3.10
Classifier: Programming Language :: Python :: 3.11
Classifier: Programming Language :: Python :: 3.12
Classifier: Programming Language :: Python :: 3.13
Classifier: Programming Language :: Python :: 3.14
Requires-Python: <3.15,>=3.10
License-File: LICENSE
License-File: LICENSES_bundled
Requires-Dist: numpy
Requires-Dist: scipy
Provides-Extra: docs
Requires-Dist: sphinx; extra == "docs"
Requires-Dist: myst-nb; extra == "docs"
Requires-Dist: matplotlib; extra == "docs"
Requires-Dist: sphinx-design; extra == "docs"
Requires-Dist: sphinx-autoapi; extra == "docs"
Requires-Dist: sphinx-copybutton; extra == "docs"
Requires-Dist: pydata-sphinx-theme; extra == "docs"
Provides-Extra: tests
Requires-Dist: pandas; extra == "tests"
Requires-Dist: pytest; extra == "tests"
Requires-Dist: pytest-cov; extra == "tests"
Requires-Dist: pytest-xdist; extra == "tests"
Provides-Extra: dev
Requires-Dist: nox; extra == "dev"
Requires-Dist: flake8; extra == "dev"
Requires-Dist: autopep8; extra == "dev"
Requires-Dist: codespell; extra == "dev"
Requires-Dist: genbadge[all]; extra == "dev"
Requires-Dist: scikit-sundae[docs,tests]; extra == "dev"
Dynamic: license-file
